README.md
setup.py
gh_things/__init__.py
gh_things/main.py
gh_things.egg-info/PKG-INFO
gh_things.egg-info/SOURCES.txt
gh_things.egg-info/dependency_links.txt
gh_things.egg-info/entry_points.txt
gh_things.egg-info/top_level.txt