Metadata-Version: 2.1
Name: gh-things
Version: 1.1.3
Summary: Companion app for the Github CLI gh to fetch machine readable information about Github objects
Home-page: https://github.com/talwrii/gh-things
Author: @readwithai
Author-email: talwrii@gmail.com
License: GPLv3
Keywords: github,gh,JSON,objects
